marulc/__init__.py
marulc/exceptions.py
marulc/nmea0183.py
marulc/nmea0183_sentence_formatters.json
marulc/nmea2000.py
marulc/nmea2000_pgn_specifications.json
marulc/parser_bases.py
marulc/utils.py
marulc-0.2.0.dist-info/METADATA
marulc-0.2.0.dist-info/WHEEL
marulc-0.2.0.dist-info/top_level.txt
marulc-0.2.0.dist-info/RECORD
