Metadata-Version: 2.1
Name: marulc
Version: 0.2.0
Summary: Maritime Unpack-Lookup-Convert
Home-page: https://github.com/MO-RISE/marulc
Author: Fredrik Olsson
Author-email: fredrik.x.olsson@ri.se
Maintainer: Fredrik Olsson
Maintainer-email: fredrik.x.olsson@ri.se
License: Apache License 2.0
Platform: UNKNOWN
Requires-Python: >=3.7
Requires-Dist: bitstruct
